nish_cmd/__init__.py
nish_cmd/cmd.py
nish_cmd-0.3.0.dist-info/METADATA
nish_cmd-0.3.0.dist-info/WHEEL
nish_cmd-0.3.0.dist-info/entry_points.txt
nish_cmd-0.3.0.dist-info/top_level.txt
nish_cmd-0.3.0.dist-info/RECORD
