Metadata-Version: 2.1
Name: nish_cmd
Version: 0.3.0
Summary: Default template for PDM package
Author-email: NishNovae <raecrowned@gmail.com>
License: MIT
Requires-Python: >=3.9
Requires-Dist: nish-lotto >=0.2.0
